workflowpy/__init__.py
workflowpy/compiler.py
workflowpy/definitions/__init__.py
workflowpy/definitions/action.py
workflowpy/magic/__init__.py
workflowpy/magic/__init__.pyi
workflowpy/magic/custom.py
workflowpy/magic/custom.pyi
workflowpy/magic/types.py
workflowpy/magic/types.pyi
workflowpy/models/__init__.py
workflowpy/models/shortcuts.py
workflowpy/modules/__init__.py
workflowpy/modules/_workflowpy/__init__.py
workflowpy/modules/_workflowpy/magic/__init__.py
workflowpy/modules/_workflowpy/magic/custom.py
workflowpy/modules/_workflowpy/magic/types.py
workflowpy/synthesizer.py
workflowpy/utils.py
workflowpy/value.py
workflowpy/value_type.py
workflowpy_shortcuts-0.1.2.dist-info/METADATA
workflowpy_shortcuts-0.1.2.dist-info/WHEEL
workflowpy_shortcuts-0.1.2.dist-info/RECORD
