Metadata-Version: 2.3
Name: workflowpy-shortcuts
Version: 0.1.2
Summary: Create iOS Shortcuts with Python code
License: MIT
Author: david-why
Author-email: david_why@outlook.com
Requires-Python: >=3.12,<4.0
Classifier: License :: OSI Approved :: MIT License
Classifier: Programming Language :: Python :: 3
Classifier: Programming Language :: Python :: 3.12
Classifier: Programming Language :: Python :: 3.13
Requires-Dist: pydantic (>=2.11.7,<3.0.0)
Project-URL: Repository, https://github.com/david-why/workflowpy
